linkmaths_quarto/__init__.py
linkmaths_quarto/link_color.py
linkquarto/__init__.py
linkquarto/link_color.py
linkquarto-0.3.0.dist-info/licenses/LICENSE
linkquarto-0.3.0.dist-info/METADATA
linkquarto-0.3.0.dist-info/WHEEL
linkquarto-0.3.0.dist-info/top_level.txt
linkquarto-0.3.0.dist-info/RECORD
