Metadata-Version: 2.4
Name: linkquarto
Version: 0.3.0
Summary: Fonction d'usage python pour ddpi.
Home-page: https://github.com/GuyNYAMSI/ddpitools
Author: GuyNyamsi
Author-email: nyamsguy@gmail.com
Classifier: Programming Language :: Python :: 3
Classifier: License :: OSI Approved :: MIT License
Classifier: Operating System :: OS Independent
Requires-Python: >=3.9
License-File: LICENSE
Dynamic: license-file
